lasier/__init__.py
lasier/adapters/__init__.py
lasier/adapters/caches/__init__.py
lasier/adapters/caches/aiocache.py
lasier/adapters/caches/base.py
lasier/adapters/caches/django.py
lasier/adapters/caches/redis.py
lasier/circuit_breaker/__init__.py
lasier/circuit_breaker/asyncio.py
lasier/circuit_breaker/base.py
lasier/circuit_breaker/rules/__init__.py
lasier/circuit_breaker/rules/base.py
lasier/circuit_breaker/rules/max_failures.py
lasier/circuit_breaker/rules/percentage_failures.py
lasier/circuit_breaker/sync.py
lasier/types.py
lasier-0.3.0.dist-info/LICENSE
lasier-0.3.0.dist-info/WHEEL
lasier-0.3.0.dist-info/METADATA
lasier-0.3.0.dist-info/RECORD
