Metadata-Version: 2.1
Name: lasier
Version: 0.3.0
Summary: A sync/async circuit breaker implementation
Home-page: https://github.com/luizalabs/lasier
License: MIT
Keywords: circuit breaker,sync,async
Author: LuizaLabs
Author-email: pypi@luizalabs.com
Requires-Python: >=3.8,<4.0
Classifier: Intended Audience :: Developers
Classifier: License :: OSI Approved :: MIT License
Classifier: Operating System :: OS Independent
Classifier: Programming Language :: Python :: 3
Classifier: Programming Language :: Python :: 3.10
Classifier: Programming Language :: Python :: 3.8
Classifier: Programming Language :: Python :: 3.9
Project-URL: Repository, https://github.com/luizalabs/lasier
